pctap_annek/__init__.py
pctap_annek/cli.py
pctap_annek-0.2.0.dist-info/entry_points.txt
pctap_annek-0.2.0.dist-info/LICENSE
pctap_annek-0.2.0.dist-info/WHEEL
pctap_annek-0.2.0.dist-info/METADATA
pctap_annek-0.2.0.dist-info/RECORD
