Metadata-Version: 2.1
Name: pctap-annek
Version: 0.2.0
Summary: Tap LDAP for PCs
License: MIT
Author: Michael MacKenna
Author-email: mmackenna@unitedfiregroup.com
Requires-Python: >=3.8,<4.0
Classifier: License :: OSI Approved :: MIT License
Classifier: Programming Language :: Python :: 3
Classifier: Programming Language :: Python :: 3.8
Classifier: Programming Language :: Python :: 3.9
Requires-Dist: click (>=7.1.2,<8.0.0)
Requires-Dist: ldap3 (>=2.9,<3.0)
